[{
        "id": "1",
        "name": "Assistance with daily life",
        "key_name": "assistance_daily_life",
        "order": "10",
        "created": "2019-10-07 14:36:49",
        "archive": "0"
    }, {
        "id": "2",
        "name": "Transport",
        "key_name": "transport",
        "order": "20",
        "created": "2019-10-07 14:36:49",
        "archive": "0"
    }, {
        "id": "3",
        "name": "Consumables",
        "key_name": "consumables",
        "order": "30",
        "created": "2019-10-07 14:37:15",
        "archive": "0"
    }, {
        "id": "4",
        "name": "Assistance with social and community participation",
        "key_name": "assistance_social_community_participation",
        "order": "40",
        "created": "2019-10-07 14:37:15",
        "archive": "0"
    }, {
        "id": "5",
        "name": "Assistive technology",
        "key_name": "assistive_technology",
        "order": "50",
        "created": "2019-10-07 14:37:38",
        "archive": "0"
    }, {
        "id": "6",
        "name": "Home modifications",
        "key_name": "home_modifications",
        "order": "60",
        "created": "2019-10-07 14:37:38",
        "archive": "0"
    }, {
        "id": "7",
        "name": "Support Coordination",
        "key_name": "support_coordination",
        "order": "70",
        "created": "2019-10-07 14:38:03",
        "archive": "0"
    }, {
        "id": "8",
        "name": "Improved living arrangements",
        "key_name": "improved_living_arrangements",
        "order": "80",
        "created": "2019-10-07 14:38:03",
        "archive": "0"
    }, {
        "id": "9",
        "name": "Increased social and community participation",
        "key_name": "increased_social_community_participation",
        "order": "90",
        "created": "2019-10-07 14:38:27",
        "archive": "0"
    }, {
        "id": "10",
        "name": "Finding and keeping a job",
        "key_name": "finding_keeping_job",
        "order": "100",
        "created": "2019-10-07 14:38:27",
        "archive": "0"
    }, {
        "id": "11",
        "name": "Improved relationships",
        "key_name": "improved_relationships",
        "order": "110",
        "created": "2019-10-07 14:38:50",
        "archive": "0"
    }, {
        "id": "12",
        "name": "Improved health and wellbeing",
        "key_name": "improved_health_wellbeing",
        "order": "120",
        "created": "2019-10-07 14:38:50",
        "archive": "0"
    }, {
        "id": "13",
        "name": "Improved learning",
        "key_name": "improved_learning",
        "order": "130",
        "created": "2019-10-07 14:39:09",
        "archive": "0"
    }, {
        "id": "14",
        "name": "Improved life choices",
        "key_name": "improved_life_choices",
        "order": "140",
        "created": "2019-10-07 14:39:09",
        "archive": "0"
    }, {
        "id": "15",
        "name": "Improved daily living skills",
        "key_name": "improved_daily_living_skills",
        "order": "150",
        "created": "2019-10-07 14:39:28",
        "archive": "0"
    },{
        "id": "16",
        "name": "Other type",
        "key_name": "other_type",
        "order": "160",
        "created": "2019-10-07 14:39:28",
        "archive": "0"
    }]