[{
        "id": "1",
        "name": "Daily Living",
        "order": "10",
        "created": "2019-10-07 14:27:24",
        "archive": "0"
    }, {
        "id": "2",
        "name": "Home",
        "order": "20",
        "created": "2019-10-07 14:27:24",
        "archive": "0"
    }, {
        "id": "3",
        "name": "Health & Wellbeing",
        "order": "30",
        "created": "2019-10-07 14:28:00",
        "archive": "0"
    }, {
        "id": "4",
        "name": "Lifelong Learning",
        "order": "40",
        "created": "2019-10-07 14:28:00",
        "archive": "0"
    }, {
        "id": "5",
        "name": "Social & Community Participation",
        "order": "50",
        "created": "2019-10-07 14:28:29",
        "archive": "0"
    }, {
        "id": "6",
        "name": "Relationships",
        "order": "60",
        "created": "2019-10-07 14:28:29",
        "archive": "0"
    }, {
        "id": "7",
        "name": "Choice & Control",
        "order": "70",
        "created": "2019-10-07 14:28:54",
        "archive": "0"
    }, {
        "id": "8",
        "name": "Work",
        "order": "80",
        "created": "2019-10-07 14:28:54",
        "archive": "0"
    }]